.coveragerc
.scrutinizer.yml
CHANGES.rst
CONTRIBUTING.rst
CREDITS.rst
LICENCE.rst
MANIFEST.in
README.rst
TODO.rst
requirements.txt
setup.cfg
setup.py
docs/assumptions.rst
docs/changelog.rst
docs/conf.py
docs/developing.rst
docs/entrypoints.rst
docs/further_reading.rst
docs/index.rst
docs/modules.rst
docs/options.rst
docs/overview.rst
docs/project.rst
docs/saruman.actions.rst
docs/saruman.app.rst
docs/saruman.conf.rst
docs/saruman.helpers.rst
docs/saruman.rst
docs/saruman.tasks.iproute2.rst
docs/saruman.tasks.kernel.rst
docs/saruman.tasks.misc.rst
docs/saruman.tasks.rst
saruman/__init__.py
saruman/__main__.py
saruman.egg-info/PKG-INFO
saruman.egg-info/SOURCES.txt
saruman.egg-info/dependency_links.txt
saruman.egg-info/entry_points.txt
saruman.egg-info/not-zip-safe
saruman.egg-info/requires.txt
saruman.egg-info/top_level.txt
saruman/actions/__init__.py
saruman/actions/start.py
saruman/app/__init__.py
saruman/app/queue.py
saruman/conf/__init__.py
saruman/conf/celery.py
saruman/conf/tasks.yaml
saruman/conf/tasks/kernel.yaml
saruman/helpers/__init__.py
saruman/helpers/check.py
saruman/helpers/config.py
saruman/helpers/error_handling.py
saruman/helpers/exceptions.py
saruman/helpers/logger.py
saruman/tasks/__init__.py
saruman/tasks/aws/__init__.py
saruman/tasks/dhcp/__init__.py
saruman/tasks/dns/__init__.py
saruman/tasks/firewall/__init__.py
saruman/tasks/iproute2/__init__.py
saruman/tasks/iproute2/interfaces.py
saruman/tasks/iptables/__init__.py
saruman/tasks/kernel/__init__.py
saruman/tasks/kernel/modprobe.py
saruman/tasks/misc/__init__.py
saruman/tasks/misc/hello_world.py
tests/__init__.py
tests/test_helloworld.py
tests/test_modprobe.py