Metadata-Version: 1.1
Name: saruman
Version: 0.3.0
Summary: A firewall that leverage AMQP workqueue ! Build by iresam for iresam !
Home-page: https://github.com/tychota/saruman
Author: tychota
Author-email: tycho.tatitscheff+saruman@gadz.org
License: MIT
Keywords: firewall,amqp,nftables,dhcp, reverse-proxy
Platform: UNKNOWN
Classifier: Development Status :: 2 - Pre-Alpha
Classifier: Environment :: Console
Classifier: Intended Audience :: System Administrators
Classifier: Natural Language :: English
Classifier: Natural Language :: French
Classifier: Operating System :: POSIX :: Linux
Classifier: Topic :: Internet :: Name Service (DNS)
Classifier: Topic :: Internet :: Proxy Servers
Classifier: Topic :: System :: Networking
Classifier: Topic :: System :: Networking :: Firewalls
Classifier: License :: OSI Approved :: MIT License
Classifier: Programming Language :: Python :: 3.3
Classifier: Programming Language :: Python :: 3.4
